polyboost/__init__.py
polyboost/polyboost.py
polyboost/models/__init__.py
polyboost/models/humdiv-final.model
polyboost/models/humvar-final.model
polyboost/models/polyboost.hv.new.model
polyboost-1.1.0.dist-info/LICENSE.md
polyboost-1.1.0.dist-info/METADATA
polyboost-1.1.0.dist-info/WHEEL
polyboost-1.1.0.dist-info/top_level.txt
polyboost-1.1.0.dist-info/RECORD
