Metadata-Version: 2.1
Name: polyboost
Version: 1.1.0
Summary: An enhanced genomic variant classifier
Home-page: https://github.com/djparente/polyboost
Author: Daniel J. Parente
Author-email: dparente@kumc.edu
License: UNKNOWN
Platform: UNKNOWN
Classifier: Programming Language :: Python :: 3
Classifier: License :: OSI Approved :: BSD License
Classifier: Operating System :: OS Independent
Requires-Python: >=3.7
Requires-Dist: numpy
Requires-Dist: xgboost
